{
  "routes": [
    {
      "method": "GET",
      "path": "/starters",
      "handler": "Starter.find",
      "config": {
        "policies": []
      }
    },
    {
      "method": "GET",
      "path": "/starters/count",
      "handler": "Starter.count",
      "config": {
        "policies": []
      }
    },
    {
      "method": "GET",
      "path": "/starters/:id",
      "handler": "Starter.findOne",
      "config": {
        "policies": []
      }
    },
    {
      "method": "POST",
      "path": "/starters",
      "handler": "Starter.create",
      "config": {
        "policies": []
      }
    },
    {
      "method": "PUT",
      "path": "/starters/:id",
      "handler": "Starter.update",
      "config": {
        "policies": []
      }
    },
    {
      "method": "DELETE",
      "path": "/starters/:id",
      "handler": "Starter.delete",
      "config": {
        "policies": []
      }
    }
  ]
}
